RandomMath/RandomMathOperations.py
RandomMath/__init__.py
apiRandomMath/__init__.py
apiRandomMath/main.py
random_math_rmaiaaaa-1.2.0.dist-info/LICENSE
random_math_rmaiaaaa-1.2.0.dist-info/METADATA
random_math_rmaiaaaa-1.2.0.dist-info/WHEEL
random_math_rmaiaaaa-1.2.0.dist-info/top_level.txt
random_math_rmaiaaaa-1.2.0.dist-info/RECORD
