Metadata-Version: 2.1
Name: random-math-rmaiaaaa
Version: 1.2.0
Summary: Random Math Package
Author-email: Rafael Maia de Souza <rmaiadesouza@gmail.com>
Project-URL: Homepage, https://github.com/rmaiaaaa/random-math
Project-URL: Bug Tracker, https://github.com/rmaiaaaa/random-math/issues
Classifier: Programming Language :: Python :: 3
Classifier: License :: OSI Approved :: MIT License
Classifier: Operating System :: OS Independent
Requires-Python: >=3.7
License-File: LICENSE
